[
  {
    "startDate": "20250101",
    "endDate": "20250102",
    "type": "NO_WORK",
    "desc": "元旦"
  },
  {
    "startDate": "20250126",
    "type": "WORK"
  },
  {
    "startDate": "20250128",
    "endDate": "20250205",
    "type": "NO_WORK",
    "desc": "春节"
  },
  {
    "startDate": "20250208",
    "type": "WORK"
  },
  {
    "startDate": "20250404",
    "endDate": "20250407",
    "type": "NO_WORK",
    "desc": "清明"
  },
  {
    "startDate": "20250427",
    "type": "WORK"
  },
  {
    "startDate": "20250501",
    "endDate": "20250506",
    "type": "NO_WORK",
    "desc": "劳动节"
  },
  {
    "startDate": "20250531",
    "endDate": "20250603",
    "type": "NO_WORK",
    "desc": "端午节"
  },
  {
    "startDate": "20250928",
    "type": "WORK"
  },
  {
    "startDate": "20251001",
    "endDate": "20251009",
    "type": "NO_WORK",
    "desc": "中秋+国庆"
  },
  {
    "startDate": "20251011",
    "type": "WORK"
  }
]